sageopt/__init__.py
sageopt/coniclifts/__init__.py
sageopt/coniclifts/base.py
sageopt/coniclifts/compilers.py
sageopt/coniclifts/cones.py
sageopt/coniclifts/reformulators.py
sageopt/coniclifts/utilities.py
sageopt/coniclifts/constraints/__init__.py
sageopt/coniclifts/constraints/constraint.py
sageopt/coniclifts/constraints/elementwise.py
sageopt/coniclifts/constraints/set_membership/__init__.py
sageopt/coniclifts/constraints/set_membership/product_cone.py
sageopt/coniclifts/constraints/set_membership/psd_cone.py
sageopt/coniclifts/constraints/set_membership/sage_cones.py
sageopt/coniclifts/constraints/set_membership/setmem.py
sageopt/coniclifts/operators/__init__.py
sageopt/coniclifts/operators/abs.py
sageopt/coniclifts/operators/affine.py
sageopt/coniclifts/operators/exp.py
sageopt/coniclifts/operators/norms.py
sageopt/coniclifts/operators/pos.py
sageopt/coniclifts/operators/relent.py
sageopt/coniclifts/operators/precompiled/__init__.py
sageopt/coniclifts/operators/precompiled/affine.py
sageopt/coniclifts/operators/precompiled/relent.py
sageopt/coniclifts/problems/__init__.py
sageopt/coniclifts/problems/problem.py
sageopt/coniclifts/problems/solvers/__init__.py
sageopt/coniclifts/problems/solvers/ecos.py
sageopt/coniclifts/problems/solvers/mosek.py
sageopt/coniclifts/problems/solvers/solver.py
sageopt/coniclifts/standards/__init__.py
sageopt/coniclifts/standards/constants.py
sageopt/interop/__init__.py
sageopt/interop/cvxpy.py
sageopt/interop/gpkit.py
sageopt/interop/scipy.py
sageopt/relaxations/__init__.py
sageopt/relaxations/constraint_generators.py
sageopt/relaxations/poly_solution_recovery.py
sageopt/relaxations/sage_polys.py
sageopt/relaxations/sage_sigs.py
sageopt/relaxations/sig_solution_recovery.py
sageopt/relaxations/symbolic_correspondences.py
sageopt/symbolic/__init__.py
sageopt/symbolic/polynomials.py
sageopt/symbolic/signomials.py
sageopt/symbolic/utilities.py
sageopt/tests/__init__.py
sageopt/tests/test_coniclifts/__init__.py
sageopt-0.5.2.dist-info/METADATA
sageopt-0.5.2.dist-info/WHEEL
sageopt-0.5.2.dist-info/top_level.txt
sageopt-0.5.2.dist-info/RECORD
