Metadata-Version: 2.1
Name: sageopt
Version: 0.5.2
Summary: Signomial and polynomial optimization via SAGE relaxations
Home-page: https://github.com/rileyjmurray/sageopt
Author: Riley John Murray
Author-email: rmurray@caltech.edu
License: UNKNOWN
Platform: UNKNOWN
Classifier: Programming Language :: Python :: 3.5
Classifier: Programming Language :: Python :: 3.6
Classifier: Programming Language :: Python :: 3.7
Classifier: Natural Language :: English
Classifier: License :: OSI Approved :: Apache Software License
Classifier: Development Status :: 4 - Beta
Classifier: Operating System :: OS Independent
Classifier: Intended Audience :: Science/Research
Classifier: Topic :: Scientific/Engineering :: Mathematics
Requires-Python: >=3.5
Requires-Dist: ecos (>=2)
Requires-Dist: numpy (>=1.14)
Requires-Dist: scipy (>=1.1)
Requires-Dist: nose2
